jwt_passwordless/__init__.py
jwt_passwordless/__version__.py
jwt_passwordless/admin.py
jwt_passwordless/apps.py
jwt_passwordless/models.py
jwt_passwordless/serializers.py
jwt_passwordless/services.py
jwt_passwordless/settings.py
jwt_passwordless/signals.py
jwt_passwordless/urls.py
jwt_passwordless/utils.py
jwt_passwordless/views.py
jwt_passwordless/migrations/0001_initial.py
jwt_passwordless/migrations/0002_auto_20200122_0424.py
jwt_passwordless/migrations/0003_callbacktoken_type.py
jwt_passwordless/migrations/0004_auto_20200125_0853.py
jwt_passwordless/migrations/0005_auto_20201117_0410.py
jwt_passwordless/migrations/__init__.py
jwt_passwordless/templates/passwordless_default_token_email.html
jwt_passwordless/templates/passwordless_default_verification_token_email.html
jwt_passwordless-1.0.4.dist-info/licenses/LICENSE
jwt_passwordless-1.0.4.dist-info/METADATA
jwt_passwordless-1.0.4.dist-info/WHEEL
jwt_passwordless-1.0.4.dist-info/top_level.txt
jwt_passwordless-1.0.4.dist-info/RECORD
