Metadata-Version: 2.4
Name: jwt-passwordless
Version: 1.0.4
Summary: Passwordless authentication for Django using JWT and supporting multiple emails per user.
Home-page: https://github.com/Hire-Abroad/jwt-passwordless
Author: Hire Abroad
Author-email: contact@hireabroad.com
License: MIT
Classifier: License :: OSI Approved :: MIT License
Classifier: Programming Language :: Python
Classifier: Programming Language :: Python :: 3
Classifier: Programming Language :: Python :: 3.6
Classifier: Programming Language :: Python :: Implementation :: CPython
Classifier: Programming Language :: Python :: Implementation :: PyPy
Classifier: Development Status :: 5 - Production/Stable
Classifier: Environment :: Web Environment
Classifier: Framework :: Django
Classifier: Intended Audience :: Developers
Classifier: Operating System :: OS Independent
Classifier: Programming Language :: Python
Classifier: Topic :: Internet :: WWW/HTTP
Requires-Python: >=3
License-File: LICENSE
Requires-Dist: Django>=2.2
Requires-Dist: djangorestframework>=3.10
Requires-Dist: djangorestframework-simplejwt>=4.4.0
Dynamic: author
Dynamic: author-email
Dynamic: classifier
Dynamic: description
Dynamic: description-content-type
Dynamic: home-page
Dynamic: license
Dynamic: license-file
Dynamic: requires-dist
Dynamic: requires-python
Dynamic: summary
